ezsynth/EZMain.py
ezsynth/__init__.py
ezsynth/utils/__init__.py
ezsynth/utils/_eb.py
ezsynth/utils/_ebsynth.py
ezsynth/utils/ebsynth.dll
ezsynth/utils/ezutils.py
ezsynth/utils/misc.py
ezsynth/utils/sequences.py
ezsynth/utils/blend/__init__.py
ezsynth/utils/blend/blender.py
ezsynth/utils/blend/histogram_blend.py
ezsynth/utils/blend/reconstruction.py
ezsynth/utils/flow_utils/OpticalFlow.py
ezsynth/utils/flow_utils/__init__.py
ezsynth/utils/flow_utils/warp.py
ezsynth/utils/flow_utils/alt_cuda_corr/__init__.py
ezsynth/utils/flow_utils/alt_cuda_corr/setup.py
ezsynth/utils/flow_utils/core/__init__.py
ezsynth/utils/flow_utils/core/corr.py
ezsynth/utils/flow_utils/core/datasets.py
ezsynth/utils/flow_utils/core/extractor.py
ezsynth/utils/flow_utils/core/raft.py
ezsynth/utils/flow_utils/core/update.py
ezsynth/utils/flow_utils/core/utils/__init__.py
ezsynth/utils/flow_utils/core/utils/augmentor.py
ezsynth/utils/flow_utils/core/utils/flow_viz.py
ezsynth/utils/flow_utils/core/utils/utils.py
ezsynth/utils/flow_utils/models/raft-kitti.pth
ezsynth/utils/flow_utils/models/raft-sintel.pth
ezsynth/utils/flow_utils/models/raft-small.pth
ezsynth/utils/guides/__init__.py
ezsynth/utils/guides/edge_detection.py
ezsynth/utils/guides/guides.py
ezsynth-2.1.1.dist-info/METADATA
ezsynth-2.1.1.dist-info/WHEEL
ezsynth-2.1.1.dist-info/top_level.txt
ezsynth-2.1.1.dist-info/RECORD
