Metadata-Version: 2.1
Name: ezsynth
Version: 2.1.1
Classifier: Programming Language :: Python :: 3
Classifier: License :: OSI Approved :: MIT License
Classifier: Operating System :: OS Independent
Requires-Python: >=3.11
Requires-Dist: torch
Requires-Dist: Pillow
Requires-Dist: numpy
Requires-Dist: phycv
Requires-Dist: opencv-contrib-python
Requires-Dist: scipy
